{
  "db_name": "SQLite",
  "query": "\nSELECT\n    id,\n    task_template_id,\n    bin_path,\n    pid,\n    created_ts,\n    start_ts,\n    stop_ts,\n    exit_status,\n    basedir\nFROM\n    task\nWHERE\n    id = ?1\n        ",
  "describe": {
    "columns": [
      {
        "name": "id",
        "ordinal": 0,
        "type_info": "Integer"
      },
      {
        "name": "task_template_id",
        "ordinal": 1,
        "type_info": "Integer"
      },
      {
        "name": "bin_path",
        "ordinal": 2,
        "type_info": "Text"
      },
      {
        "name": "pid",
        "ordinal": 3,
        "type_info": "Integer"
      },
      {
        "name": "created_ts",
        "ordinal": 4,
        "type_info": "Integer"
      },
      {
        "name": "start_ts",
        "ordinal": 5,
        "type_info": "Integer"
      },
      {
        "name": "stop_ts",
        "ordinal": 6,
        "type_info": "Integer"
      },
      {
        "name": "exit_status",
        "ordinal": 7,
        "type_info": "Integer"
      },
      {
        "name": "basedir",
        "ordinal": 8,
        "type_info": "Text"
      }
    ],
    "parameters": {
      "Right": 1
    },
    "nullable": [
      false,
      false,
      false,
      true,
      false,
      true,
      true,
      true,
      false
    ]
  },
  "hash": "aa889577343230c742c9775320abf1691c6396036ddb0583927b1c912eae257c"
}
